ibioml/__init__.py
ibioml/models.py
ibioml/plots.py
ibioml/preprocess_data.py
ibioml/trainer.py
ibioml/tuner.py
ibioml/utils/__init__.py
ibioml/utils/data_scaler.py
ibioml/utils/evaluators.py
ibioml/utils/model_factory.py
ibioml/utils/pipeline_utils.py
ibioml/utils/plot_functions.py
ibioml/utils/plot_styles.py
ibioml/utils/preprocessing_funcs.py
ibioml/utils/splitters.py
ibioml/utils/trainer_funcs.py
ibioml/utils/tuner_funcs.py
ibioml-0.1.2.dist-info/licenses/LICENSE
ibioml-0.1.2.dist-info/METADATA
ibioml-0.1.2.dist-info/WHEEL
ibioml-0.1.2.dist-info/top_level.txt
ibioml-0.1.2.dist-info/RECORD
