Metadata-Version: 2.4
Name: ibioml
Version: 0.1.2
Summary: ML toolkit for neuro decoding experiments at IBIoBA
Author: Juani
License-File: LICENSE
Requires-Dist: numpy
Requires-Dist: pandas
Requires-Dist: scikit-learn
Requires-Dist: torch
Requires-Dist: matplotlib
Requires-Dist: scipy
Requires-Dist: seaborn
Dynamic: author
Dynamic: license-file
Dynamic: requires-dist
Dynamic: summary
